{
  "safes": [
    {
      "id": 1,
      "name": "דרור",
      "goalAmount": 100,
      "goalName": "לגו",
      "photoUrl": "images/dror.jpeg",
      "bonusCountdownInDays": 17
    },
    {
      "id": 2,
      "name": "שחר",
      "goalAmount": 70,
      "goalName": "טרקטור",
      "photoUrl": "images/shachar.jpeg",
      "bonusCountdownInDays": 23
    }
  ],
  "transactions": [
    {
      "id": 1,
      "safeId": 1,
      "amount": -9,
      "type": 2,
      "reason": "סליים",
      "timestamp": 1664021559000
    },
    {
      "id": 1,
      "safeId": 1,
      "amount": 10,
      "type": 0,
      "reason": "הפקדה שבועית",
      "timestamp": 1664277942992
    },
    {
      "id": 1,
      "safeId": 2,
      "amount": 10,
      "type": 0,
      "reason": "הפקדה שבועית",
      "timestamp": 1656331959000
    },
    {
      "id": 2,
      "safeId": 2,
      "amount": -7,
      "type": 2,
      "reason": "מחברת",
      "timestamp": 1663071159000
    }
  ]
}
